selene/.DS_Store
selene/__init__.py
selene/_managed.py
selene/api/.DS_Store
selene/api/__init__.py
selene/api/base/__init__.py
selene/api/shared/__init__.py
selene/common/__init__.py
selene/common/data_structures/__init__.py
selene/common/data_structures/persistent.py
selene/common/fp.py
selene/common/helpers.py
selene/common/none_object.py
selene/common/predicate.py
selene/core/__init__.py
selene/core/command.py
selene/core/condition.py
selene/core/conditions.py
selene/core/configuration.py
selene/core/configuration.pyi
selene/core/entity.py
selene/core/entity.pyi
selene/core/exceptions.py
selene/core/locator.py
selene/core/match.py
selene/core/query.py
selene/core/wait.py
selene/py.typed
selene/support/.DS_Store
selene/support/__init__.py
selene/support/_extensions/__init__.py
selene/support/_extensions/webdriver_manager/__init__.py
selene/support/_extensions/webdriver_manager/patch.py
selene/support/_logging.py
selene/support/by.py
selene/support/conditions/__init__.py
selene/support/conditions/be.py
selene/support/conditions/have.py
selene/support/conditions/not_.py
selene/support/shared/__init__.py
selene/support/shared/browser.py
selene/support/shared/config.py
selene/support/shared/jquery_style.py
selene/support/webdriver.py
selene_with_new_wdm-2.2.1.dist-info/LICENSE
selene_with_new_wdm-2.2.1.dist-info/METADATA
selene_with_new_wdm-2.2.1.dist-info/WHEEL
selene_with_new_wdm-2.2.1.dist-info/RECORD
