Metadata-Version: 2.1
Name: selene_with_new_wdm
Version: 2.2.1
Summary: Selene 2.0.0rc4 + webdriver-manager-4.0.2
Home-page: https://yashaka.github.io/selene/
License: MIT
Keywords: testing,selenium,selenide,browser,pageobject,widget,wrapper
Author: Yevhen Halitsyn
Author-email: yevhen.halitsyn@nixs.com
Requires-Python: >=3.9,<4.0
Classifier: Development Status :: 4 - Beta
Classifier: Environment :: Web Environment
Classifier: Intended Audience :: Developers
Classifier: License :: OSI Approved :: Apache Software License
Classifier: License :: OSI Approved :: MIT License
Classifier: Natural Language :: English
Classifier: Operating System :: OS Independent
Classifier: Programming Language :: Python
Classifier: Programming Language :: Python :: 3
Classifier: Programming Language :: Python :: 3.9
Classifier: Programming Language :: Python :: 3.10
Classifier: Programming Language :: Python :: 3.11
Classifier: Programming Language :: Python :: 3.12
Classifier: Topic :: Internet :: WWW/HTTP :: Browsers
Classifier: Topic :: Software Development :: Libraries :: Application Frameworks
Classifier: Topic :: Software Development :: Libraries :: Python Modules
Classifier: Topic :: Software Development :: Testing
Requires-Dist: future
Requires-Dist: selenium (>=4.9.0)
Requires-Dist: typing-extensions (>=4.6.1)
Requires-Dist: webdriver-manager (==4.0.2)
Project-URL: Changelog, https://github.com/yashaka/selene/releases
Project-URL: Documentation, https://yashaka.github.io/selene/
Project-URL: Repository, https://github.com/yashaka/selene/
